daruma_py2compat/__init__.py
daruma_py2compat/daruma_module.py
daruma_py2compat/functions.py
daruma_py2compat/models.py
daruma_py2compat/data/AAindex553-Normal-X0.feature
daruma_py2compat/data/CNN3_128_9_NN2_121_128.weight
daruma_py2compat-0.1.0.dist-info/METADATA
daruma_py2compat-0.1.0.dist-info/WHEEL
daruma_py2compat-0.1.0.dist-info/entry_points.txt
daruma_py2compat-0.1.0.dist-info/top_level.txt
daruma_py2compat-0.1.0.dist-info/RECORD
